README.md
crtsh.py
setup.cfg
setup.py
crtsh.egg-info/PKG-INFO
crtsh.egg-info/SOURCES.txt
crtsh.egg-info/dependency_links.txt
crtsh.egg-info/requires.txt
crtsh.egg-info/top_level.txt