Metadata-Version: 1.1
Name: crtsh
Version: 0.3.1
Summary: (Unofficial) Python API for https://crt.sh
Home-page: https://github.com/PaulSec/crt.sh
Author: PaulSec
Author-email: UNKNOWN
License: UNKNOWN
Download-URL: https://github.com/PaulSec/crt.sh/archive/0.3.1.tar.gz
Keywords: crt.sh,ssl,certificates,osint
Platform: UNKNOWN
